AUTHORS.txt
CHANGES.txt
LICENSE.txt
MANIFEST.in
Makefile
README.rst
requirements.txt
setup.py
speedrack/__init__.py
speedrack/aps.py
speedrack/cmdline.py
speedrack/context_processors.py
speedrack/decorators.py
speedrack/filer.py
speedrack/filters.py
speedrack/models.py
speedrack/notification.py
speedrack/status.py
speedrack/timing.py
speedrack/views.py
speedrack.egg-info/PKG-INFO
speedrack.egg-info/SOURCES.txt
speedrack.egg-info/dependency_links.txt
speedrack.egg-info/entry_points.txt
speedrack.egg-info/not-zip-safe
speedrack.egg-info/requires.txt
speedrack.egg-info/top_level.txt
speedrack/config/__init__.py
speedrack/config/__init__.pyc
speedrack/config/default.py
speedrack/config/dev_requirements.pip
speedrack/config/test.yaml
speedrack/constants/__init__.py
speedrack/constants/task_params.py
speedrack/static/css/bootstrap-responsive.css
speedrack/static/css/bootstrap-responsive.min.css
speedrack/static/css/bootstrap.css
speedrack/static/css/bootstrap.min.css
speedrack/static/css/style.css
speedrack/static/ico/stopwatch_run.ico
speedrack/static/img/glyphicons-halflings-white.png
speedrack/static/img/glyphicons-halflings.png
speedrack/static/js/bootstrap.js
speedrack/static/js/bootstrap.min.js
speedrack/static/js/script.js
speedrack/static/js/libs/jquery-1.7.1.min.js
speedrack/static/js/libs/modernizr-2.5.3-respond-1.1.0.min.js
speedrack/static/js/libs/bootstrap/alert.js
speedrack/static/js/libs/bootstrap/bootstrap.js
speedrack/static/js/libs/bootstrap/bootstrap.min.js
speedrack/static/js/libs/bootstrap/button.js
speedrack/static/js/libs/bootstrap/carousel.js
speedrack/static/js/libs/bootstrap/collapse.js
speedrack/static/js/libs/bootstrap/dropdown.js
speedrack/static/js/libs/bootstrap/modal.js
speedrack/static/js/libs/bootstrap/popover.js
speedrack/static/js/libs/bootstrap/scrollspy.js
speedrack/static/js/libs/bootstrap/tab.js
speedrack/static/js/libs/bootstrap/tooltip.js
speedrack/static/js/libs/bootstrap/transition.js
speedrack/static/js/libs/bootstrap/typeahead.js
speedrack/templates/_single_task.html.jinja
speedrack/templates/config.html.jinja
speedrack/templates/debug.html.jinja
speedrack/templates/file.html.jinja
speedrack/templates/help.html.jinja
