Metadata-Version: 1.1
Name: speedrack
Version: 0.5.1
Summary: yet another task runner, with web interface and execution history
Home-page: https://bitbucket.org/clinthowarth/speedrack
Author: Clint Howarth
Author-email: clint.howarth@gmail.com
License: BSD License
Keywords: speedrack cron webcron
Platform: UNKNOWN
Classifier: Development Status :: 4 - Beta
Classifier: Environment :: Web Environment
Classifier: License :: OSI Approved :: BSD License
Classifier: Programming Language :: Python :: 2
Classifier: Topic :: System :: Monitoring
Classifier: Topic :: System :: Logging
